spotpuppy/__init__.py
spotpuppy/core/__init__.py
spotpuppy/core/foot_positions.py
spotpuppy/core/leg_control.py
spotpuppy/core/quadruped_controller.py
spotpuppy/models/__init__.py
spotpuppy/models/basic_quadruped.py
spotpuppy/models/quadruped_base.py
spotpuppy/rotation/__init__.py
spotpuppy/rotation/arduino_rotation_sensor.py
spotpuppy/rotation/dummy_rotation_sensor.py
spotpuppy/rotation/mpu6050_rotation_sensor.py
spotpuppy/rotation/rotation_sensor_base.py
spotpuppy/servo/__init__.py
spotpuppy/servo/redboard_modified_lib.py
spotpuppy/servo/redboard_servo_controller.py
spotpuppy/servo/servo_controller_base.py
spotpuppy/servo/servokit_servo_controller.py
spotpuppy/servo/unity_servo_controller.py
spotpuppy/utils/__init__.py
spotpuppy/utils/json_serialiser.py
spotpuppy/utils/pid_control.py
spotpuppy/utils/time_util.py
spotpuppy-0.1.7.dist-info/LICENSE.txt
spotpuppy-0.1.7.dist-info/METADATA
spotpuppy-0.1.7.dist-info/WHEEL
spotpuppy-0.1.7.dist-info/top_level.txt
spotpuppy-0.1.7.dist-info/RECORD
