Metadata-Version: 2.1
Name: spotpuppy
Version: 0.1.7
Summary: Package for controlling a dynamically balanced quadruped
Home-page: UNKNOWN
Author: Josh Pattman
Author-email: josh.pattman@gmail.com
License: UNKNOWN
Download-URL: https://github.com/JoshPattman/spotpuppy/archive/refs/tags/0.1.7.tar.gz
Platform: UNKNOWN
Classifier: Development Status :: 3 - Alpha
Requires-Dist: numpy
Requires-Dist: scipy
